django2_alexa/__init__.py
django2_alexa/admin.py
django2_alexa/apps.py
django2_alexa/models.py
django2_alexa/tests.py
django2_alexa/views.py
django2_alexa/interfaces/__init__.py
django2_alexa/interfaces/alexa.py
django2_alexa/interfaces/request/__init__.py
django2_alexa/interfaces/request/alexa.py
django2_alexa/interfaces/request/audio_player.py
django2_alexa/interfaces/request/base.py
django2_alexa/interfaces/request/intent.py
django2_alexa/interfaces/response/__init__.py
django2_alexa/interfaces/response/alexa.py
django2_alexa/interfaces/response/audio_player.py
django2_alexa/interfaces/response/cards.py
django2_alexa/interfaces/response/output_speech.py
django2_alexa/migrations/__init__.py
django2_alexa/utils/__init__.py
django2_alexa/utils/exceptions.py
django2_alexa/utils/s3_verification.py
django2_alexa/utils/alexa/__init__.py
django2_alexa/utils/alexa/cards.py
django2_alexa/utils/alexa/locales.py
django2_alexa/utils/enums/__init__.py
django2_alexa/utils/enums/dialog_states.py
django2_alexa/utils/enums/locales.py
django2_alexa/utils/enums/play_behavior.py
django2_alexa-0.1.4.dist-info/LICENSE
django2_alexa-0.1.4.dist-info/METADATA
django2_alexa-0.1.4.dist-info/WHEEL
django2_alexa-0.1.4.dist-info/top_level.txt
django2_alexa-0.1.4.dist-info/RECORD
