Metadata-Version: 2.1
Name: django2-alexa
Version: 0.1.4
Summary: Django app for easily creating Amazon Alexa Skills
Home-page: https://github.com/timwoocker/django-alexa
Author: Tim Woocker & Malte Mosler
Author-email: tim.woocker@googlemail.com
License: UNKNOWN
Platform: UNKNOWN
Classifier: Programming Language :: Python :: 3
Classifier: License :: OSI Approved :: MIT License
Classifier: Operating System :: OS Independent
